pipspect-0.3.dist-info/DESCRIPTION.rst
pipspect-0.3.dist-info/METADATA
pipspect-0.3.dist-info/RECORD
pipspect-0.3.dist-info/WHEEL
pipspect-0.3.dist-info/entry_points.txt
pipspect-0.3.dist-info/metadata.json
pipspect-0.3.dist-info/top_level.txt
src/__init__.py
src/pipspect.py
src/test/__init__.py
src/test/mock.py
src/test/test.py
