Metadata-Version: 2.0
Name: pipspect
Version: 0.3
Summary: A small CLI tool to inspect your modules, especially those installed via pip
Home-page: https://github.com/tohyongcheng/pipspect
Author: Yong Cheng Toh
Author-email: tohyongcheng@gmail.com
License: MIT
Keywords: module,inspect,pip,classes,builtin,functions,methods
Platform: UNKNOWN
Classifier: Development Status :: 3 - Alpha
Classifier: Environment :: Console
Classifier: Intended Audience :: Developers
Classifier: License :: OSI Approved :: MIT License
Classifier: Programming Language :: Python
Classifier: Topic :: Software Development :: Testing
Classifier: Programming Language :: Python :: 2
